vkms/__init__.py
vkms/actions.py
vkms/argparser.py
vkms/attachments.py
vkms/database.py
vkms/main.py
vkms/messages.py
vkms/peers.py
vkms/saver.py
vkms/users.py
vkms/utils.py
vkms/version.py
vkms/templates/peer.html
vkms-1.0.2.dist-info/LICENSE
vkms-1.0.2.dist-info/METADATA
vkms-1.0.2.dist-info/WHEEL
vkms-1.0.2.dist-info/entry_points.txt
vkms-1.0.2.dist-info/top_level.txt
vkms-1.0.2.dist-info/RECORD
