Metadata-Version: 2.1
Name: vkms
Version: 1.0.2
Summary: Utility for saving messages from the VK social network
Author-email: Yaroslav Kikel <yaroslav.kikel.06@inbox.ru>
License: GPL-3.0-only
Project-URL: Homepage, https://github.com/YariKartoshe4ka/vk-messages-saver
Keywords: api,parser,vk,messages,saver
Classifier: Development Status :: 5 - Production/Stable
Classifier: License :: OSI Approved :: GNU General Public License v3 (GPLv3)
Classifier: Operating System :: OS Independent
Classifier: Programming Language :: Python
Classifier: Programming Language :: Python :: 3
Classifier: Programming Language :: Python :: 3 :: Only
Classifier: Programming Language :: Python :: 3.8
Classifier: Programming Language :: Python :: 3.9
Classifier: Programming Language :: Python :: 3.10
Classifier: Programming Language :: Python :: 3.11
Classifier: Programming Language :: Python :: Implementation :: CPython
Classifier: Topic :: Utilities
Classifier: Environment :: Console
License-File: LICENSE
Requires-Dist: pathvalidate (<4,>=2.5)
Requires-Dist: requests (<3,>=2.24)
Requires-Dist: Jinja2 (<4,>=3.1)
Requires-Dist: minify-html (<1,>=0.8)
Requires-Dist: vk (<4,>=3.0)
Requires-Dist: SQLAlchemy (<3,>=1.4)
